ha_franklin/__init__.py
ha_franklin/cli.py
ha_franklin/monitor.py
ha_franklin/utils.py
ha_franklin-0.1.2.dist-info/METADATA
ha_franklin-0.1.2.dist-info/WHEEL
ha_franklin-0.1.2.dist-info/entry_points.txt
ha_franklin-0.1.2.dist-info/RECORD
