Metadata-Version: 2.1
Name: ha-franklin
Version: 0.1.2
Summary: ha-franklin monitors CUPSD queues and writes information to MQTT for Home Assistant
License: Apache 2.0
Author: Joe Block
Author-email: jpb@unixorn.net
Requires-Python: >=3.10.0,<4.0
Classifier: License :: Other/Proprietary License
Classifier: Programming Language :: Python :: 3
Classifier: Programming Language :: Python :: 3.10
Classifier: Programming Language :: Python :: 3.11
Requires-Dist: ha-mqtt-discoverable (>=0.8.1,<0.9.0)
Requires-Dist: pyaml (>=21.10.1,<22.0.0)
Requires-Dist: shell (>=1.0.1,<2.0.0)
